odoo/addons/runbot_send_email/README.rst
odoo/addons/runbot_send_email/__init__.py
odoo/addons/runbot_send_email/__manifest__.py
odoo/addons/runbot_send_email/data/runbot_send_email_data.xml
odoo/addons/runbot_send_email/demo/ir_mail_server_demo.xml
odoo/addons/runbot_send_email/models/__init__.py
odoo/addons/runbot_send_email/models/runbot_build.py
odoo/addons/runbot_send_email/models/runbot_repo.py
odoo/addons/runbot_send_email/static/img/dc.png
odoo/addons/runbot_send_email/static/img/dg.png
odoo/addons/runbot_send_email/static/img/gi.png
odoo/addons/runbot_send_email/static/img/is.png
odoo/addons/runbot_send_email/static/img/sm.png
odoo/addons/runbot_send_email/static/img/watch_build.png
odoo/addons/runbot_send_email/static/img/watch_repo.jpeg
odoo/addons/runbot_send_email/static/src/js/runbot.js
odoo/addons/runbot_send_email/tests/__init__.py
odoo/addons/runbot_send_email/tests/test_runbot_send_email.py
odoo/addons/runbot_send_email/views/assets.xml
odoo/addons/runbot_send_email/views/runbot_send_email_view.xml
odoo11_addon_runbot_send_email-11.0.1.0.0.dist-info/DESCRIPTION.rst
odoo11_addon_runbot_send_email-11.0.1.0.0.dist-info/METADATA
odoo11_addon_runbot_send_email-11.0.1.0.0.dist-info/RECORD
odoo11_addon_runbot_send_email-11.0.1.0.0.dist-info/WHEEL
odoo11_addon_runbot_send_email-11.0.1.0.0.dist-info/metadata.json
odoo11_addon_runbot_send_email-11.0.1.0.0.dist-info/top_level.txt
